Controller/Controller.sv
module Controller(
    input clock,
    input reset,
    input zero,
    input cnt_eq,
    output set_busy,
    output clr_busy,
    output ld_cnt,
    output cnt_en,
    output addr_sel,
    output zero_we);

    typedef enum logic[1:0] {INIT, NORMAL, ZERO} state, nxt_state;

    always_ff @(posedge clock) begin 
        
        
    end

endmodule

Controller/Datapath.sv
module register #(parameter ADDRWIDTH = 6)(
    input load, 
    input [ADDRWIDTH-1:0] din,
    output logic [ADDRWIDTH-1:0] dout
    );

    logic [ADDRWIDTH-1:0] m;

    assign dout = m;

    always_latch begin
       if(load) m = din;
    end
    
endmodule

module Upcounter #(parameter ADDRWIDTH = 6)(
    input clock,
    input load, en,
    input [ADDRWIDTH-1:0] din,
    output logic [ADDRWIDTH-1:0] dout
    );

    logic [ADDRWIDTH-1:0] count;

    assign dout = count;

    always_ff @(posedge clock) begin 
        if(load)
            count <= din;
        else if(en)
            count <= count + 1'b 1;  
        else count <= count;     
    end
    
endmodule

//module comparator #(parameter ADDRWIDTH = 6) (
//    input [ADDRWIDTH-1:0] din_b, din_a,
//    output logic aEQb
//    );
//
//    assign aEQb = (din_b === din_a) ? 1 : 0;
//endmodule

module Memory #(parameter ADDRWIDTH = 6, DATAWIDTH = 8) (
    input [ADDRWIDTH-1:0] addr,
    input [DATAWIDTH-1:0] din,
    input we,
    input clock,
    output logic [DATAWIDTH-1:0] dout
    );

    logic [DATAWIDTH-1:0] mem [2**ADDRWIDTH-1:0];

    assign dout = mem[addr];

    always_ff @(posedge clock) begin
        if(we)
            mem[addr] <= din;
        else mem <= mem;
    end
    
endmodule

module MUX #(parameter WIDTH = 6, N = 2)(
    input [N-1:0][WIDTH-1:0] V,
    input [$clog2(N)-1:0] S,
    output logic [WIDTH-1:0] Y
    );

    assign Y = V[S];
    
endmodule

module JK_FF(
    input J, K, clock, 
    output logic Q
    );

    always_ff @(posedge clock) begin
        if({J,K} == 2'b11) 
            Q <= ~Q;
        else if({J,K} == 2'b10)
            Q <= 1'b1;
        else if({J,K} == 2'b01)
            Q <= 1'b0;
        else if({J,K} == 2'b00)
            Q <= Q;
    end
           
endmodule


module datapath(clock, ld_high, ld_low, addr, din, write, set_busy,
    clr_busy, ld_cnt, cnt_en, addr_sel, zero_we, cnt_eq, dout, busy);
    parameter ADDRWIDTH = 6;
    parameter DATAWIDTH = 8;
    input clock;
    input ld_high, ld_low;
    input [ADDRWIDTH-1:0] addr;
    input [DATAWIDTH-1:0] din;
    input write;
    input set_busy;
    input clr_busy;
    input ld_cnt;
    input cnt_en;
    input addr_sel;
    input zero_we;
    output logic cnt_eq;
    output logic [DATAWIDTH-1:0] dout;
    output logic busy;
 
    logic [ADDRWIDTH-1:0] dout1, dout2, dout_up;

    register #(ADDRWIDTH) R1_Inst(ld_high, addr, dout1);

    register #(ADDRWIDTH) R2_Inst(ld_low, addr, dout2);

    Upcounter #(ADDRWIDTH) UP_Inst(clock, ld_cnt, cnt_en, dout2, dout_up);   

   // comparator #(ADDRWIDTH) comp_Inst(dout1, dout_up, cnt_eq);

    assign cnt_eq = (dout1 === dout_up);

    logic [DATAWIDTH-1:0] memDatIn;
    logic [ADDRWIDTH-1:0] memAdrIn;

    MUX #(.N(2), .WIDTH(ADDRWIDTH)) mux1_Inst(.V({dout_up, addr}), .S(addr_sel), .Y(memAdrIn));

    MUX #(.N(2), .WIDTH(DATAWIDTH)) mux2_Inst(.V({{DATAWIDTH{1'b0}}, din}), .S(addr_sel), .Y(memDatIn));

    JK_FF JK_Inst(set_busy, clr_busy, clock, busy);

    logic OR;

    assign OR = write | zero_we;

    Memory #(ADDRWIDTH, DATAWIDTH) mem_Inst(memAdrIn, memDatIn, OR, clock, dout);


endmodule

Controller/mz.sv
module mz(clock, reset, ld_high, ld_low, addr, din, write, zero,
    dout, busy);
    parameter ADDRWIDTH = 6;
    parameter DATAWIDTH = 8;
    input clock;
    input reset;
    input ld_high, ld_low;
    input [ADDRWIDTH-1:0] addr;
    input [DATAWIDTH-1:0] din;
    input write;
    input zero;
    output logic [DATAWIDTH-1:0] dout;
    output logic busy;

    logic set_busy, clr_busy, ld_cnt, cnt_en, addr_sel, zero_we, cnt_eq; 

    datapath  #(ADDRWIDTH, DATAWIDTH) dp_Inst
    (.clock(clock), 
    .ld_high(ld_high), 
    .ld_low(ld_low), 
    .addr(addr), 
    .din(din), 
    .write(write), 
    .set_busy(set_busy),
    .clr_busy(clr_busy), 
    .ld_cnt(ld_cnt), 
    .cnt_en(cnt_en), 
    .addr_sel(addr_sel), 
    .zero_we(zero_we), 
    .cnt_eq(cnt_eq), 
    .dout(dout), 
    .busy(busy));

    Controller C_Inst
    (.clock(clock),
    .reset(reset),
    .zero(zero),
    .cnt_eq(cnt_eq),
    .set_busy(set_busy),
    .clr_busy(clr_busy),
    .ld_cnt(ld_cnt),
    .cnt_en(cnt_en),
    .addr_sel(addr_sel),
    .zero_we(zero_we));
    
    
endmodule

Controller/tb.sv
module tb;

    parameter ADDRWIDTH = 6;
    parameter DATAWIDTH = 8;
    bit clock;
    logic reset;
    logic ld_high, ld_low;
    logic [ADDRWIDTH-1:0] addr;
    logic [DATAWIDTH-1:0] din;
    logic write;
    logic zero;
    logic [DATAWIDTH-1:0] dout;
    logic busy;

    mz #(ADDRWIDTH, DATAWIDTH) T(clock, reset, ld_high, ld_low, addr, din, write, zero,
                                 dout, busy);

    bit ERR = 0;
    logic [DATAWIDTH-1:0] d;

    logic [ADDRWIDTH-1:0] randomaddr1 = 15;
    logic [ADDRWIDTH-1:0] randomaddr2 = (1 << ADDRWIDTH-1) - 1; //31

    initial begin
        clock = '1;
        forever #10 clock = ~clock;
    end

    // write data in normal mode
    task Writedata(input [ADDRWIDTH-1:0] a, input [DATAWIDTH-1:0] d);
        begin
            @(negedge clock);
            wait(!busy);
            ld_high = '0;
            ld_low = '0;
            addr = a;
            din = d;
            zero = '0;
            write = '1;

            repeat(2) @(negedge clock);
            write = '0;
        end
        
    endtask 

    // read data in normal mode
    task Readdata(input [ADDRWIDTH-1:0] a, output [DATAWIDTH-1:0] d);
    begin
        ld_high = '0;
        ld_low = '0;
        din = 'x;
        zero = '0;
        write = '0;
        addr = a;

        @(negedge clock);
        d = dout;
    end
        
    endtask 

    task NOP;
    begin
        @(negedge clock);
        wait(!busy);
    end
    endtask 

    //write zeros in zero mode in memory
    task WriteZero(input [ADDRWIDTH-1:0] low, input [ADDRWIDTH-1:0] high);
    begin
        @(negedge clock);
        wait(!busy);
        zero = '0;
        write = '0;
        addr = low;
        #10;
        ld_low = '1;
        #10;
        ld_low = '0;
        #10;
        addr = high;
        #10;
        ld_high = '1;
        #10;
        ld_high = '0;
        addr = 'x;
        din = 'x;
        #10;
        zero = '1;
       
        @(posedge clock);
        @(negedge clock);
        zero = '0;
        @(posedge clock);
        wait(!busy);       
    end        
    endtask

    /*
    * Use hierarchical instance name of memory array to directly verify memory contents
    * All addresses outside the range should contain data equal to the memory address
    * If zero is 1, then all memory at addresses inside the range should be zero.
    * Otherwise, they should also be the same as the address.  Report any errors and
    * set Errors flag.
    *
    */
    task VerifyMemory(input [ADDRWIDTH-1:0] low, [ADDRWIDTH-1:0] high, input bit zero);    
        for(int i = 0; i<(1<<(ADDRWIDTH)); i++) begin
            if(((low>high) /*wraparound*/ && ((i>=low) || (i<=high)))  || ((low<=high) && ((i>=low) && (i<=high))))
            begin
                if(T.dp_Inst.mem_Inst.mem[i] !== (zero ? '0 : i)) begin
                    $display("VMem[%0h] = %0h is not equal to %0h", i, T.dp_Inst.mem_Inst.mem[i], (zero ? '0 : i));
                    ERR = '1;
                end
            end

            else begin
                if(T.dp_Inst.mem_Inst.mem[i] !== i) begin
                $display("VMem[%0h] = %0h is not equal to %0h", i, T.dp_Inst.mem_Inst.mem[i], (zero ? '0 : i));
                ERR = '1;
                end
            end
        end        
    endtask

    /*
    * Use normal mode reads verify memory contents
    * All addresses outside the range should contain data equal to the memory address
    * If zero is 1, then all memory at addresses inside the range should be zero.
    * Otherwise, they should also be the same as the address.  Report any errors and
    * set Errors flag.
    *
    */
    task VerifyReadMemory(input [ADDRWIDTH-1:0] low, [ADDRWIDTH-1:0] high, input bit zero);
    logic [DATAWIDTH-1:0] d;
    
        for(int i = 0; i<(1<<(ADDRWIDTH)); i++) begin
            Readdata(i,d);
            if(((low>high) /*wraparound*/ && ((i>=low) || (i<=high)))  || ((low<=high) && ((i>=low) && (i<=high))))
            begin
                if(d !== (zero ? '0 : i)) begin
                    $display("RMem[%0h] = %0h is not equal to %0h", i, d, (zero ? '0 : i));
                    ERR = '1;
                end
            end

            else begin
                if(d !== i) begin
                $display("RMem[%0h] = %0h is not equal to %0h", i, d, (zero ? '0 : i));
                ERR = '1;
                end
            end
        end        
    endtask

    task DumpMem;
    for(int i = 0; i<(1<<(ADDRWIDTH)); i++)
        begin
           $display("DMem[%0d] = %0d", i, T.dp_Inst.mem_Inst.mem[i]); 
        end        
    endtask


    initial begin
        $dumpfile("dump.vcd"); $dumpvars;
        $display("********TB Begins********");
        reset = '1;
        repeat(2) @(negedge clock);
        reset = '0;

        //1. Use "normal" interface to write a pattern to each memory location and confirm
        $display("checking for initalization of memory to known values in normal mode");
        for (int i = 0; i < (1 << (ADDRWIDTH)); i++)
        	Writedata(i[ADDRWIDTH-1:0],i[DATAWIDTH-1:0]);
            NOP; 
            VerifyReadMemory('0,(1 << ADDRWIDTH)-1,'0);
            VerifyMemory('0,(1 << ADDRWIDTH)-1,'0);
            //DumpMem;

            
        //2. Use "zero" mode to zero a single arbitrary row R1 = R2, confirm others unchanged
        $display("checking for zero of range (%d,%d)",randomaddr1,randomaddr1);
        WriteZero(randomaddr1,randomaddr1);
        NOP; 
        //DumpMem;
        VerifyMemory(randomaddr1,randomaddr1,'1);
        

        $display("checking for restoration of single value range (normal mode)");
        Writedata(randomaddr1,randomaddr1);
        NOP; 
        //DumpMem;
        VerifyMemory(randomaddr1,randomaddr1,'0);
       

        //3. Use "zero" mode for range with R2 > R1, confirm others unchanged
        $display("checking for zero of  range (%d,%d)",randomaddr2,randomaddr1);
        WriteZero(randomaddr2,randomaddr1);
        NOP;
        //DumpMem; 
        VerifyMemory(randomaddr2,randomaddr1,'1);

        $display("checking for restoration of constraint range (normal mode)");
        for (int i = 0; i <= randomaddr1; i++) begin
        	Writedata(i[ADDRWIDTH-1:0],i);
            NOP;
        end 
        for (int i = randomaddr2; i <= (1 << ADDRWIDTH)-1; i++) begin
        	Writedata(i[ADDRWIDTH-1:0],i);
            NOP;
        end
        //DumpMem; 
        VerifyMemory('0,(1 << ADDRWIDTH)-1,'0);



        //4. Use "zero" mode for range with R2 < R1, confirm others unchanged
        $display("checking for zero of  range (%d,%d)",randomaddr1,randomaddr2);
        WriteZero(randomaddr1,randomaddr2);
        NOP;
        //DumpMem; 
        VerifyMemory(randomaddr1,randomaddr2,'1); 

        $display("checking for restoration of constraint range (normal mode)");
        for (int i = randomaddr1; i <= randomaddr2; i++) begin
        	Writedata(i[ADDRWIDTH-1:0],i);
            NOP;
        end 
        //DumpMem; 
        VerifyMemory('0,(1 << ADDRWIDTH)-1,'0);

        //5. check for all zeros for the entire memory
        for(int i = 0; i <= (1<<ADDRWIDTH)-1; i++) begin
            WriteZero(0, (1<<ADDRWIDTH)-1);
            NOP;
            VerifyMemory('0,(1 << ADDRWIDTH)-1,'1);
        end

        if (ERR)
	    $display("\n\n\n*** FAILED ***\n\n\n");
        else
	    $display("\n\n\n*** PASSED ***\n\n\n");
    
        $stop();

    end
   

endmodule

Controller/sim/dump.vcd
$date
	Wed Jan 15 21:12:42 2025
$end
$version
	QuestaSim Version 2021.3_1
$end
$timescale
	1ns
$end

$scope module tb $end
$var parameter 32 ! ADDRWIDTH $end
$var parameter 32 " DATAWIDTH $end
$var reg 1 # clock $end
$var reg 1 $ reset $end
$var reg 1 % ld_high $end
$var reg 1 & ld_low $end
$var reg 6 ' addr [5:0] $end
$var reg 8 ( din [7:0] $end
$var reg 1 ) write $end
$var reg 1 * zero $end
$var reg 8 + dout [7:0] $end
$var reg 1 , busy $end
$var reg 1 - ERR $end
$var reg 8 . d [7:0] $end
$var reg 6 / randomaddr1 [5:0] $end
$var reg 6 0 randomaddr2 [5:0] $end

$scope task Writedata $end
$var reg 6 1 a [5:0] $end
$var reg 8 2 d [7:0] $end
$upscope $end

$scope task Readdata $end
$var reg 6 3 a [5:0] $end
$var reg 8 4 d [7:0] $end
$upscope $end

$scope task NOP $end
$upscope $end

$scope task WriteZero $end
$var reg 6 5 low [5:0] $end
$var reg 6 6 high [5:0] $end
$upscope $end

$scope task VerifyMemory $end
$var reg 6 7 low [5:0] $end
$var reg 6 8 high [5:0] $end
$var reg 1 9 zero $end
$upscope $end

$scope task VerifyReadMemory $end
$var reg 6 : low [5:0] $end
$var reg 6 ; high [5:0] $end
$var reg 1 < zero $end
$var reg 8 = d [7:0] $end
$upscope $end

$scope task DumpMem $end
$upscope $end

$scope module T $end
$var parameter 32 > ADDRWIDTH $end
$var parameter 32 ? DATAWIDTH $end
$var wire 1 @ clock $end
$var wire 1 A reset $end
$var wire 1 B ld_high $end
$var wire 1 C ld_low $end
$var wire 1 D addr [5] $end
$var wire 1 E addr [4] $end
$var wire 1 F addr [3] $end
$var wire 1 G addr [2] $end
$var wire 1 H addr [1] $end
$var wire 1 I addr [0] $end
$var wire 1 J din [7] $end
$var wire 1 K din [6] $end
$var wire 1 L din [5] $end
$var wire 1 M din [4] $end
$var wire 1 N din [3] $end
$var wire 1 O din [2] $end
$var wire 1 P din [1] $end
$var wire 1 Q din [0] $end
$var wire 1 R write $end
$var wire 1 S zero $end
$var reg 8 T dout [7:0] $end
$var reg 1 U busy $end
$var reg 1 V set_busy $end
$var reg 1 W clr_busy $end
$var reg 1 X ld_cnt $end
$var reg 1 Y cnt_en $end
$var reg 1 Z addr_sel $end
$var reg 1 [ zero_we $end
$var reg 1 \ cnt_eq $end

$scope module dp_Inst $end
$var parameter 32 ] ADDRWIDTH $end
$var parameter 32 ^ DATAWIDTH $end
$var wire 1 @ clock $end
$var wire 1 B ld_high $end
$var wire 1 C ld_low $end
$var wire 1 D addr [5] $end
$var wire 1 E addr [4] $end
$var wire 1 F addr [3] $end
$var wire 1 G addr [2] $end
$var wire 1 H addr [1] $end
$var wire 1 I addr [0] $end
$var wire 1 J din [7] $end
$var wire 1 K din [6] $end
$var wire 1 L din [5] $end
$var wire 1 M din [4] $end
$var wire 1 N din [3] $end
$var wire 1 O din [2] $end
$var wire 1 P din [1] $end
$var wire 1 Q din [0] $end
$var wire 1 R write $end
$var wire 1 _ set_busy $end
$var wire 1 ` clr_busy $end
$var wire 1 a ld_cnt $end
$var wire 1 b cnt_en $end
$var wire 1 c addr_sel $end
$var wire 1 d zero_we $end
$var reg 1 e cnt_eq $end
$var reg 8 f dout [7:0] $end
$var reg 1 g busy $end
$var reg 6 h dout1 [5:0] $end
$var reg 6 i dout2 [5:0] $end
$var reg 6 j dout_up [5:0] $end
$var reg 8 k memDatIn [7:0] $end
$var reg 6 l memAdrIn [5:0] $end
$var reg 1 m OR $end

$scope module R1_Inst $end
$var parameter 32 n ADDRWIDTH $end
$var wire 1 B load $end
$var wire 1 D din [5] $end
$var wire 1 E din [4] $end
$var wire 1 F din [3] $end
$var wire 1 G din [2] $end
$var wire 1 H din [1] $end
$var wire 1 I din [0] $end
$var reg 6 o dout [5:0] $end
$var reg 6 p m [5:0] $end
$upscope $end

$scope module R2_Inst $end
$var parameter 32 q ADDRWIDTH $end
$var wire 1 C load $end
$var wire 1 D din [5] $end
$var wire 1 E din [4] $end
$var wire 1 F din [3] $end
$var wire 1 G din [2] $end
$var wire 1 H din [1] $end
$var wire 1 I din [0] $end
$var reg 6 r dout [5:0] $end
$var reg 6 s m [5:0] $end
$upscope $end

$scope module UP_Inst $end
$var parameter 32 t ADDRWIDTH $end
$var wire 1 @ clock $end
$var wire 1 a load $end
$var wire 1 b en $end
$var wire 1 u din [5] $end
$var wire 1 v din [4] $end
$var wire 1 w din [3] $end
$var wire 1 x din [2] $end
$var wire 1 y din [1] $end
$var wire 1 z din [0] $end
$var reg 6 { dout [5:0] $end
$var reg 6 | count [5:0] $end
$upscope $end

$scope module mux1_Inst $end
$var parameter 32 } WIDTH $end
$var parameter 32 ~ N $end
$var wire 1 I V [0] $end
$var wire 1 H V [1] $end
$var wire 1 G V [2] $end
$var wire 1 F V [3] $end
$var wire 1 E V [4] $end
$var wire 1 D V [5] $end
$var wire 1 !! V [6] $end
$var wire 1 "! V [7] $end
$var wire 1 #! V [8] $end
$var wire 1 $! V [9] $end
$var wire 1 %! V [10] $end
$var wire 1 &! V [11] $end
$var wire 1 c S [0] $end
$var reg 6 '! Y [5:0] $end
$upscope $end

$scope module mux2_Inst $end
$var parameter 32 (! WIDTH $end
$var parameter 32 )! N $end
$var wire 1 Q V [0] $end
$var wire 1 P V [1] $end
$var wire 1 O V [2] $end
$var wire 1 N V [3] $end
$var wire 1 M V [4] $end
$var wire 1 L V [5] $end
$var wire 1 K V [6] $end
$var wire 1 J V [7] $end
$var wire 1 *! V [8] $end
$var wire 1 +! V [9] $end
$var wire 1 ,! V [10] $end
$var wire 1 -! V [11] $end
$var wire 1 .! V [12] $end
$var wire 1 /! V [13] $end
$var wire 1 0! V [14] $end
$var wire 1 1! V [15] $end
$var wire 1 c S [0] $end
$var reg 8 2! Y [7:0] $end
$upscope $end

$scope module JK_Inst $end
$var wire 1 _ J $end
$var wire 1 ` K $end
$var wire 1 @ clock $end
$var reg 1 3! Q $end
$upscope $end

$scope module mem_Inst $end
$var parameter 32 4! ADDRWIDTH $end
$var parameter 32 5! DATAWIDTH $end
$var wire 1 6! addr [5] $end
$var wire 1 7! addr [4] $end
$var wire 1 8! addr [3] $end
$var wire 1 9! addr [2] $end
$var wire 1 :! addr [1] $end
$var wire 1 ;! addr [0] $end
$var wire 1 <! din [7] $end
$var wire 1 =! din [6] $end
$var wire 1 >! din [5] $end
$var wire 1 ?! din [4] $end
$var wire 1 @! din [3] $end
$var wire 1 A! din [2] $end
$var wire 1 B! din [1] $end
$var wire 1 C! din [0] $end
$var wire 1 D! we $end
$var wire 1 @ clock $end
$var reg 8 E! dout [7:0] $end
$upscope $end
$upscope $end

$scope module C_Inst $end
$var wire 1 @ clock $end
$var wire 1 A reset $end
$var wire 1 S zero $end
$var wire 1 F! cnt_eq $end
$var reg 1 G! set_busy $end
$var reg 1 H! clr_busy $end
$var reg 1 I! ld_cnt $end
$var reg 1 J! cnt_en $end
$var reg 1 K! addr_sel $end
$var reg 1 L! zero_we $end
$var reg 2 M! state [1:0] $end
$var reg 2 N! nxt_state [1:0] $end
$upscope $end
$upscope $end
$upscope $end

$scope begin std $end
$upscope $end
$enddefinitions $end
#0
$dumpvars
1#
1$
x%
x&
bx '
bx (
x)
x*
bx +
x,
bx T
xU
0V
1W
0X
0Y
0Z
0[
1\
1e
bx f
xg
bx h
bx i
bx j
bx o
bx p
bx r
bx s
bx {
bx |
bx k
bx l
bx '!
bx 2!
x3!
xm
bx E!
0G!
1H!
0I!
0J!
0K!
0L!
b0 M!
b0 N!
0-
bx .
b1111 /
b11111 0
bx 1
bx 2
bx 3
bx 4
bx 5
bx 6
bx 7
bx 8
09
bx :
bx ;
0<
bx =
b110 !
b1000 "
b110 >
b1000 ?
b110 ]
b1000 ^
b110 n
b110 q
b110 t
b110 }
b10 ~
b1000 (!
b10 )!
b110 4!
b1000 5!
xS
xR
xQ
xP
xO
xN
xM
xL
xK
xJ
xI
xH
xG
xF
xE
xD
xC
xB
1A
1@
1F!
0d
0c
0b
0a
1`
0_
xD!
xC!
xB!
xA!
x@!
x?!
x>!
x=!
x<!
x;!
x:!
x9!
x8!
x7!
x6!
0*!
0+!
0,!
0-!
0.!
0/!
00!
01!
x!!
x"!
x#!
x$!
x%!
x&!
xz
xy
xx
xw
xv
xu
$end
#10
0#
0@
#20
1#
1@
03!
0g
0U
0,
#30
0#
0@
0$
b0 1
b0 2
0A
#40
1#
1@
#50
0#
0@
0%
0&
b0 '
b0 (
0*
1)
0Q
0P
0O
0N
0M
0L
0K
0J
1R
1m
b0 2!
b0 k
1D!
0C!
0B!
0A!
0@!
0?!
0>!
0=!
0<!
0B
0C
0I
0H
0G
0F
0E
0D
0S
b0 '!
b0 l
0;!
0:!
09!
08!
07!
06!
#60
1#
1@
b0 E!
b0 f
b0 T
b0 +
#70
0#
0@
#80
1#
1@
#90
0#
0@
0)
b1 1
b1 2
0R
0m
0D!
#100
1#
1@
#110
0#
0@
b1 '
b1 (
1)
1Q
1R
1m
b1 2!
b1 k
1D!
1C!
1I
b1 '!
b1 l
1;!
bx E!
bx f
bx T
bx +
#120
1#
1@
b1 E!
b1 f
b1 T
b1 +
#130
0#
0@
#140
1#
1@
#150
0#
0@
0)
b10 1
b10 2
0R
0m
0D!
#160
1#
1@
#170
0#
0@
b10 '
b10 (
1)
0Q
1P
1R
1m
b10 2!
b10 k
1D!
0C!
1B!
0I
1H
b10 '!
b10 l
0;!
1:!
bx E!
bx f
bx T
bx +
#180
1#
1@
b10 E!
b10 f
b10 T
b10 +
#190
0#
0@
#200
1#
1@
#210
0#
0@
0)
b11 1
b11 2
0R
0m
0D!
#220
1#
1@
#230
0#
0@
b11 '
b11 (
1)
1Q
1R
1m
b11 2!
b11 k
1D!
1C!
1I
b11 '!
b11 l
1;!
bx E!
bx f
bx T
bx +
#240
1#
1@
b11 E!
b11 f
b11 T
b11 +
#250
0#
0@
#260
1#
1@
#270
0#
0@
0)
b100 1
b100 2
0R
0m
0D!
#280
1#
1@
#290
0#
0@
b100 '
b100 (
1)
0Q
0P
1O
1R
1m
b100 2!
b100 k
1D!
0C!
0B!
1A!
0I
0H
1G
b100 '!
b100 l
0;!
0:!
19!
bx E!
bx f
bx T
bx +
#300
1#
1@
b100 E!
b100 f
b100 T
b100 +
#310
0#
0@
#320
1#
1@
#330
0#
0@
0)
b101 1
b101 2
0R
0m
0D!
#340
1#
1@
#350
0#
0@
b101 '
b101 (
1)
1Q
1R
1m
b101 2!
b101 k
1D!
1C!
1I
b101 '!
b101 l
1;!
bx E!
bx f
bx T
bx +
#360
1#
1@
b101 E!
b101 f
b101 T
b101 +
#370
0#
0@
#380
1#
1@
#390
0#
0@
0)
b110 1
b110 2
0R
0m
0D!
#400
1#
1@
#410
0#
0@
b110 '
b110 (
1)
0Q
1P
1R
1m
b110 2!
b110 k
1D!
0C!
1B!
0I
1H
b110 '!
b110 l
0;!
1:!
bx E!
bx f
bx T
bx +
#420
1#
1@
b110 E!
b110 f
b110 T
b110 +
#430
0#
0@
#440
1#
1@
#450
0#
0@
0)
b111 1
b111 2
0R
0m
0D!
#460
1#
1@
#470
0#
0@
b111 '
b111 (
1)
1Q
1R
1m
b111 2!
b111 k
1D!
1C!
1I
b111 '!
b111 l
1;!
bx E!
bx f
bx T
bx +
#480
1#
1@
b111 E!
b111 f
b111 T
b111 +
#490
0#
0@
#500
1#
1@
#510
0#
0@
0)
b1000 1
b1000 2
0R
0m
0D!
#520
1#
1@
#530
0#
0@
b1000 '
b1000 (
1)
0Q
0P
0O
1N
1R
1m
b1000 2!
b1000 k
1D!
0C!
0B!
0A!
1@!
0I
0H
0G
1F
b1000 '!
b1000 l
0;!
0:!
09!
18!
bx E!
bx f
bx T
bx +
#540
1#
1@
b1000 E!
b1000 f
b1000 T
b1000 +
#550
0#
0@
#560
1#
1@
#570
0#
0@
0)
b1001 1
b1001 2
0R
0m
0D!
#580
1#
1@
#590
0#
0@
b1001 '
b1001 (
1)
1Q
1R
1m
b1001 2!
b1001 k
1D!
1C!
1I
b1001 '!
b1001 l
1;!
bx E!
bx f
bx T
bx +
#600
1#
1@
b1001 E!
b1001 f
b1001 T
b1001 +
#610
0#
0@
#620
1#
1@
#630
0#
0@
0)
b1010 1
b1010 2
0R
0m
0D!
#640
1#
1@
#650
0#
0@
b1010 '
b1010 (
1)
0Q
1P
1R
1m
b1010 2!
b1010 k
1D!
0C!
1B!
0I
1H
b1010 '!
b1010 l
0;!
1:!
bx E!
bx f
bx T
bx +
#660
1#
1@
b1010 E!
b1010 f
b1010 T
b1010 +
#670
0#
0@
#680
1#
1@
#690
0#
0@
0)
b1011 1
b1011 2
0R
0m
0D!
#700
1#
1@
#710
0#
0@
b1011 '
b1011 (
1)
1Q
1R
1m
b1011 2!
b1011 k
1D!
1C!
1I
b1011 '!
b1011 l
1;!
bx E!
bx f
bx T
bx +
#720
1#
1@
b1011 E!
b1011 f
b1011 T
b1011 +
#730
0#
0@
#740
1#
1@
#750
0#
0@
0)
b1100 1
b1100 2
0R
0m
0D!
#760
1#
1@
#770
0#
0@
b1100 '
b1100 (
1)
0Q
0P
1O
1R
1m
b1100 2!
b1100 k
1D!
0C!
0B!
1A!
0I
0H
1G
b1100 '!
b1100 l
0;!
0:!
19!
bx E!
bx f
bx T
bx +
#780
1#
1@
b1100 E!
b1100 f
b1100 T
b1100 +
#790
0#
0@
#800
1#
1@
#810
0#
0@
0)
b1101 1
b1101 2
0R
0m
0D!
#820
1#
1@
#830
0#
0@
b1101 '
b1101 (
1)
1Q
1R
1m
b1101 2!
b1101 k
1D!
1C!
1I
b1101 '!
b1101 l
1;!
bx E!
bx f
bx T
bx +
#840
1#
1@
b1101 E!
b1101 f
b1101 T
b1101 +
#850
0#
0@
#860
1#
1@
#870
0#
0@
0)
b1110 1
b1110 2
0R
0m
0D!
#880
1#
1@
#890
0#
0@
b1110 '
b1110 (
1)
0Q
1P
1R
1m
b1110 2!
b1110 k
1D!
0C!
1B!
0I
1H
b1110 '!
b1110 l
0;!
1:!
bx E!
bx f
bx T
bx +
#900
1#
1@
b1110 E!
b1110 f
b1110 T
b1110 +
#910
0#
0@
#920
1#
1@
#930
0#
0@
0)
b1111 1
b1111 2
0R
0m
0D!
#940
1#
1@
#950
0#
0@
b1111 '
b1111 (
1)
1Q
1R
1m
b1111 2!
b1111 k
1D!
1C!
1I
b1111 '!
b1111 l
1;!
bx E!
bx f
bx T
bx +
#960
1#
1@
b1111 E!
b1111 f
b1111 T
b1111 +
#970
0#
0@
#980
1#
1@
#990
0#
0@
0)
b10000 1
b10000 2
0R
0m
0D!
#1000
1#
1@
#1010
0#
0@
b10000 '
b10000 (
1)
0Q
0P
0O
0N
1M
1R
1m
b10000 2!
b10000 k
1D!
0C!
0B!
0A!
0@!
1?!
0I
0H
0G
0F
1E
b10000 '!
b10000 l
0;!
0:!
09!
08!
17!
bx E!
bx f
bx T
bx +
#1020
1#
1@
b10000 E!
b10000 f
b10000 T
b10000 +
#1030
0#
0@
#1040
1#
1@
#1050
0#
0@
0)
b10001 1
b10001 2
0R
0m
0D!
#1060
1#
1@
#1070
0#
0@
b10001 '
b10001 (
1)
1Q
1R
1m
b10001 2!
b10001 k
1D!
1C!
1I
b10001 '!
b10001 l
1;!
bx E!
bx f
bx T
bx +
#1080
1#
1@
b10001 E!
b10001 f
b10001 T
b10001 +
#1090
0#
0@
#1100
1#
1@
#1110
0#
0@
0)
b10010 1
b10010 2
0R
0m
0D!
#1120
1#
1@
#1130
0#
0@
b10010 '
b10010 (
1)
0Q
1P
1R
1m
b10010 2!
b10010 k
1D!
0C!
1B!
0I
1H
b10010 '!
b10010 l
0;!
1:!
bx E!
bx f
bx T
bx +
#1140
1#
1@
b10010 E!
b10010 f
b10010 T
b10010 +
#1150
0#
0@
#1160
1#
1@
#1170
0#
0@
0)
b10011 1
b10011 2
0R
0m
0D!
#1180
1#
1@
#1190
0#
0@
b10011 '
b10011 (
1)
1Q
1R
1m
b10011 2!
b10011 k
1D!
1C!
1I
b10011 '!
b10011 l
1;!
bx E!
bx f
bx T
bx +
#1200
1#
1@
b10011 E!
b10011 f
b10011 T
b10011 +
#1210
0#
0@
#1220
1#
1@
#1230
0#
0@
0)
b10100 1
b10100 2
0R
0m
0D!
#1240
1#
1@
#1250
0#
0@
b10100 '
b10100 (
1)
0Q
0P
1O
1R
1m
b10100 2!
b10100 k
1D!
0C!
0B!
1A!
0I
0H
1G
b10100 '!
b10100 l
0;!
0:!
19!
bx E!
bx f
bx T
bx +
#1260
1#
1@
b10100 E!
b10100 f
b10100 T
b10100 +
#1270
0#
0@
#1280
1#
1@
#1290
0#
0@
0)
b10101 1
b10101 2
0R
0m
0D!
#1300
1#
1@
#1310
0#
0@
b10101 '
b10101 (
1)
1Q
1R
1m
b10101 2!
b10101 k
1D!
1C!
1I
b10101 '!
b10101 l
1;!
bx E!
bx f
bx T
bx +
#1320
1#
1@
b10101 E!
b10101 f
b10101 T
b10101 +
#1330
0#
0@
#1340
1#
1@
#1350
0#
0@
0)
b10110 1
b10110 2
0R
0m
0D!
#1360
1#
1@
#1370
0#
0@
b10110 '
b10110 (
1)
0Q
1P
1R
1m
b10110 2!
b10110 k
1D!
0C!
1B!
0I
1H
b10110 '!
b10110 l
0;!
1:!
bx E!
bx f
bx T
bx +
#1380
1#
1@
b10110 E!
b10110 f
b10110 T
b10110 +
#1390
0#
0@
#1400
1#
1@
#1410
0#
0@
0)
b10111 1
b10111 2
0R
0m
0D!
#1420
1#
1@
#1430
0#
0@
b10111 '
b10111 (
1)
1Q
1R
1m
b10111 2!
b10111 k
1D!
1C!
1I
b10111 '!
b10111 l
1;!
bx E!
bx f
bx T
bx +
#1440
1#
1@
b10111 E!
b10111 f
b10111 T
b10111 +
#1450
0#
0@
#1460
1#
1@
#1470
0#
0@
0)
b11000 1
b11000 2
0R
0m
0D!
#1480
1#
1@
